pymc_extras/__init__.py
pymc_extras/deserialize.py
pymc_extras/linearmodel.py
pymc_extras/model_builder.py
pymc_extras/printing.py
pymc_extras/prior.py
pymc_extras/distributions/__init__.py
pymc_extras/distributions/continuous.py
pymc_extras/distributions/discrete.py
pymc_extras/distributions/histogram_utils.py
pymc_extras/distributions/timeseries.py
pymc_extras/distributions/multivariate/__init__.py
pymc_extras/distributions/multivariate/r2d2m2cp.py
pymc_extras/distributions/transforms/__init__.py
pymc_extras/distributions/transforms/partial_order.py
pymc_extras/gp/__init__.py
pymc_extras/gp/latent_approx.py
pymc_extras/inference/__init__.py
pymc_extras/inference/fit.py
pymc_extras/inference/dadvi/__init__.py
pymc_extras/inference/dadvi/dadvi.py
pymc_extras/inference/laplace_approx/__init__.py
pymc_extras/inference/laplace_approx/find_map.py
pymc_extras/inference/laplace_approx/idata.py
pymc_extras/inference/laplace_approx/laplace.py
pymc_extras/inference/laplace_approx/scipy_interface.py
pymc_extras/inference/pathfinder/__init__.py
pymc_extras/inference/pathfinder/idata.py
pymc_extras/inference/pathfinder/importance_sampling.py
pymc_extras/inference/pathfinder/lbfgs.py
pymc_extras/inference/pathfinder/pathfinder.py
pymc_extras/inference/smc/__init__.py
pymc_extras/inference/smc/sampling.py
pymc_extras/model/__init__.py
pymc_extras/model/model_api.py
pymc_extras/model/marginal/__init__.py
pymc_extras/model/marginal/distributions.py
pymc_extras/model/marginal/graph_analysis.py
pymc_extras/model/marginal/marginal_model.py
pymc_extras/model/transforms/__init__.py
pymc_extras/model/transforms/autoreparam.py
pymc_extras/preprocessing/__init__.py
pymc_extras/preprocessing/standard_scaler.py
pymc_extras/statespace/__init__.py
pymc_extras/statespace/core/__init__.py
pymc_extras/statespace/core/compile.py
pymc_extras/statespace/core/representation.py
pymc_extras/statespace/core/statespace.py
pymc_extras/statespace/filters/__init__.py
pymc_extras-0.7.0.dist-info/METADATA
pymc_extras-0.7.0.dist-info/WHEEL
pymc_extras-0.7.0.dist-info/licenses/LICENSE
pymc_extras-0.7.0.dist-info/RECORD
