Metadata-Version: 2.4
Name: pymc-extras
Version: 0.7.0
Summary: A home for new additions to PyMC, which may include unusual probability distribitions, advanced model fitting algorithms, or any code that may be inappropriate to include in the pymc repository, but may want to be made available to users.
Project-URL: Documentation, https://pymc-extras.readthedocs.io/
Project-URL: Repository, https://github.com/pymc-devs/pymc-extras.git
Project-URL: Issues, https://github.com/pymc-devs/pymc-extras/issues
Author-email: PyMC Developers <pymc.devs@gmail.com>
License: =======
License-File: LICENSE
Keywords: bayesian,machine learning,mcmc,probability,sampling,statistics
Classifier: Development Status :: 5 - Production/Stable
Classifier: Intended Audience :: Science/Research
Classifier: License :: OSI Approved :: Apache Software License
Classifier: Operating System :: OS Independent
Classifier: Programming Language :: Python
Classifier: Programming Language :: Python :: 3
Classifier: Programming Language :: Python :: 3.11
Classifier: Programming Language :: Python :: 3.12
Classifier: Programming Language :: Python :: 3.13
Classifier: Topic :: Scientific/Engineering
Classifier: Topic :: Scientific/Engineering :: Mathematics
Requires-Python: >=3.11
Requires-Dist: better-optimize>=0.1.5
Requires-Dist: preliz>=0.20.0
Requires-Dist: pydantic>=2.0.0
Requires-Dist: pymc>=5.27.0
Requires-Dist: pytensor>=2.36.3
Requires-Dist: scikit-learn
Provides-Extra: complete
Requires-Dist: dask[complete]<2025.1.1; extra == 'complete'
Requires-Dist: xhistogram; extra == 'complete'
Provides-Extra: dask-histogram
Requires-Dist: dask[complete]<2025.1.1; extra == 'dask-histogram'
Requires-Dist: xhistogram; extra == 'dask-histogram'
Provides-Extra: dev
Requires-Dist: blackjax>=0.12; extra == 'dev'
Requires-Dist: dask[all]<2025.1.1; extra == 'dev'
Requires-Dist: pytest-mock; extra == 'dev'
Requires-Dist: pytest>=6.0; extra == 'dev'
Requires-Dist: statsmodels; extra == 'dev'
Provides-Extra: docs
Requires-Dist: nbsphinx>=0.4.2; extra == 'docs'
Requires-Dist: pymc-sphinx-theme>=0.16; extra == 'docs'
Requires-Dist: sphinx>=4.0; extra == 'docs'
Provides-Extra: histogram
Requires-Dist: xhistogram; extra == 'histogram'
